[

  { "name": "Adult Chicken", "type": "Processed" },
  { "name": "Adult Cow", "type": "Processed" },
  { "name": "Adult Pig", "type": "Processed" },
  { "name": "Adult Sheep", "type": "Processed" },
  { "name": "Aelan Spice", "type": "Processed" },
  { "name": "Animal Fat", "type": "Processed" },
  { "name": "Apple", "type": "Processed" },
  { "name": "Armored Raptor Nestling", "type": "Processed" },
  { "name": "Ash Beam", "type": "Processed" },
  { "name": "Ash Board", "type": "Processed" },
  { "name": "Ash Log", "type": "Processed" },
  { "name": "Ash Mulch", "type": "Processed" },
  { "name": "Ash Paper", "type": "Processed" },
  { "name": "Ash Plating", "type": "Processed" },
  { "name": "Ash Plank", "type": "Processed" },
  { "name": "Ash Saw Dust", "type": "Processed" },
  { "name": "Ash Timber", "type": "Processed" },
  { "name": "Ash Warp", "type": "Processed" },
  { "name": "Ash Woodchips", "type": "Processed" },
  { "name": "Baby Lamb", "type": "Processed" },
  { "name": "Baby Piglet", "type": "Processed" },
  { "name": "Barley", "type": "Processed" },
  { "name": "Basalt Armor Mold", "type": "Processed" },
  { "name": "Basalt Ashlar Block", "type": "Processed" },
  { "name": "Basalt Brick", "type": "Processed" },
  { "name": "Basalt Clay", "type": "Processed" },
  { "name": "Basalt Fragments", "type": "Processed" },
  { "name": "Basalt Mortar", "type": "Processed" },
  { "name": "Basalt Sand", "type": "Processed" },
  { "name": "Basalt Weapon Mold", "type": "Processed" },
  { "name": "Bear Bone", "type": "Processed" },
  { "name": "Bear Carcass", "type": "Processed" },
  { "name": "Bear Cub", "type": "Processed" },
  { "name": "Bear Fur", "type": "Processed" },
  { "name": "Bear Hide", "type": "Processed" },
  { "name": "Bear Hide Strap", "type": "Processed" },
  { "name": "Bear Leather", "type": "Processed" },
  { "name": "Bear Meat", "type": "Processed" },
  { "name": "Beef", "type": "Processed" },
  { "name": "Black Ink", "type": "Processed" },
  { "name": "Blackberry", "type": "Processed" },
  { "name": "Bloodied Spiritbloom Powder", "type": "Processed" },
  { "name": "Bloodied Bolt", "type": "Processed" },
  { "name": "Bloodoak Thread", "type": "Processed" },
  { "name": "Blue Ink", "type": "Processed" },
  { "name": "Bluebell Bolt", "type": "Processed" },
  { "name": "Bluebell Thread", "type": "Processed" },
  { "name": "Bluegill Fillet", "type": "Processed" },
{ "name": "Boar Bone", "type": "Processed" },
  { "name": "Boar Carcass", "type": "Processed" },
  { "name": "Boar Hide", "type": "Processed" },
  { "name": "Boar Leather", "type": "Processed" },
  { "name": "Boar Meat", "type": "Processed" },
  { "name": "Boar Pup", "type": "Processed" },
  { "name": "Braidwood Beam", "type": "Processed" },
  { "name": "Braidwood Board", "type": "Processed" },
  { "name": "Braidwood Log", "type": "Processed" },
  { "name": "Braidwood Mulch", "type": "Processed" },
  { "name": "Braidwood Paper", "type": "Processed" },
  { "name": "Braidwood Plating", "type": "Processed" },
  { "name": "Braidwood Plank", "type": "Processed" },
  { "name": "Braidwood Saw Dust", "type": "Processed" },
  { "name": "Braidwood Timber", "type": "Processed" },
  { "name": "Braidwood Warp", "type": "Processed" },
  { "name": "Braidwood Woodchips", "type": "Processed" },
  { "name": "Brass Armor Plating", "type": "Processed" },
  { "name": "Brass Chain Mail", "type": "Processed" },
  { "name": "Brass Ingot", "type": "Processed" },
  { "name": "Brew Bear Cub", "type": "Processed" },
  { "name": "Bronze Armor Plating", "type": "Processed" },
  { "name": "Bronze Chain Mail", "type": "Processed" },
  { "name": "Bronze Ingot", "type": "Processed" },
  { "name": "Butter", "type": "Processed" },
  { "name": "Carrot", "type": "Processed" },
  { "name": "Celery", "type": "Processed" },
  { "name": "Charcoal", "type": "Processed" },
  { "name": "Chicken Carcass", "type": "Processed" },
  { "name": "Chicken Carcass", "type": "Processed" },
  { "name": "Chicken Egg", "type": "Processed" },
  { "name": "Chicken Feed", "type": "Processed" },
  { "name": "Chicken Meat", "type": "Processed" },
  { "name": "Coke", "type": "Processed" },
  { "name": "Cooking Oil", "type": "Processed" },
  { "name": "Copper Armor Plating", "type": "Processed" },
  { "name": "Copper Chain Mail", "type": "Processed" },
  { "name": "Copper Fragments", "type": "Processed" },
  { "name": "Copper Ingot", "type": "Processed" },
  { "name": "Corn", "type": "Processed" },
  { "name": "Corrupted Ash Timber", "type": "Processed" },
  { "name": "Corrupted Chili Flakes", "type": "Processed" },
  { "name": "Cotton", "type": "Processed" },
  { "name": "Cotton Bolt", "type": "Processed" },
  { "name": "Cotton Thread", "type": "Processed" },
  { "name": "Cow Carcass", "type": "Processed" },
  { "name": "Cow Carcass", "type": "Processed" },
  { "name": "Cut Emerald", "type": "Processed" },
  { "name": "Cut Halcyonite", "type": "Processed" },
  { "name": "Cut Lumadon", "type": "Processed" },
  { "name": "Cut Ruby", "type": "Processed" },
  { "name": "Cut Sapphire", "type": "Processed" },
  { "name": "Daffodil Bolt", "type": "Processed" },
  { "name": "Daffodil Mulch", "type": "Processed" },
  { "name": "Daffodil Powder", "type": "Processed" },
  { "name": "Daffodil Thread", "type": "Processed" },
  { "name": "Dawnbreaker Cub", "type": "Processed" },
  { "name": "Deer Carcass", "type": "Processed" },
  { "name": "Divination Mirror", "type": "Processed" },
  { "name": "Dough", "type": "Processed" },
  { "name": "Drake Of The Canopy Hatchling", "type": "Processed" },
  { "name": "Dried Ash Beam", "type": "Processed" },
  { "name": "Dried Ash Board", "type": "Processed" },
  { "name": "Dried Ash Log", "type": "Processed" },
  { "name": "Dried Ash Plank", "type": "Processed" },
  { "name": "Dried Braidwood Beam", "type": "Processed" },
  { "name": "Dried Braidwood Board", "type": "Processed" },
  { "name": "Dried Braidwood Log", "type": "Processed" },
  { "name": "Dried Braidwood Plank", "type": "Processed" },
  { "name": "Dried Eastern Hemlock Beam", "type": "Processed" },
  { "name": "Dried Eastern Hemlock Board", "type": "Processed" },
  { "name": "Dried Eastern Hemlock Log", "type": "Processed" },
  { "name": "Dried Eastern Hemlock Plank", "type": "Processed" },
  { "name": "Dried Oak Beam", "type": "Processed" },
  { "name": "Dried Oak Board", "type": "Processed" },
  { "name": "Dried Oak Log", "type": "Processed" },
  { "name": "Dried Oak Plank", "type": "Processed" },
  { "name": "Dried Weeping Willow Beam", "type": "Processed" },
  { "name": "Dried Weeping Willow Board", "type": "Processed" },
  { "name": "Dried Weeping Willow Log", "type": "Processed" },
  { "name": "Dried Weeping Willow Plank", "type": "Processed" },
  { "name": "Dried Western Larch Beam", "type": "Processed" },
  { "name": "Dried Western Larch Board", "type": "Processed" },
  { "name": "Dried Western Larch Log", "type": "Processed" },
  { "name": "Dried Western Larch Plank", "type": "Processed" },
  { "name": "Eastern Hemlock Beam", "type": "Processed" },
  { "name": "Eastern Hemlock Board", "type": "Processed" },
  { "name": "Eastern Hemlock Log", "type": "Processed" },
  { "name": "Eastern Hemlock Mulch", "type": "Processed" },
  { "name": "Eastern Hemlock Paper", "type": "Processed" },
  { "name": "Eastern Hemlock Plating", "type": "Processed" },
  { "name": "Eastern Hemlock Plank", "type": "Processed" },
  { "name": "Eastern Hemlock Saw Dust", "type": "Processed" },
  { "name": "Eastern Hemlock Timber", "type": "Processed" },
  { "name": "Eastern Hemlock Warp", "type": "Processed" },
  { "name": "Eastern Hemlock Woodchips", "type": "Processed" },
  { "name": "Ebon Omen Foal", "type": "Processed" },
  { "name": "Embroidered Siege Banner", "type": "Processed" },
  { "name": "Emerald Powder", "type": "Processed" },
  { "name": "Ethanol", "type": "Processed" },
  { "name": "Fairrunner Hatchling", "type": "Processed" },
  { "name": "Flax Mulch", "type": "Processed" },
  { "name": "Flour", "type": "Processed" },
  { "name": "Flax", "type": "Processed" },
  { "name": "Giant Bluebell Mulch", "type": "Processed" },
  { "name": "Giant Bluebell Powder", "type": "Processed" },
  { "name": "Giant Bullywog Bone", "type": "Processed" },
  { "name": "Giant Bullywog Carcass", "type": "Processed" },
  { "name": "Giant Bullywog Hide", "type": "Processed" },
  { "name": "Giant Bullywog Leather", "type": "Processed" },
  { "name": "Giant Bullywog Meat", "type": "Processed" },
  { "name": "Giant Bullywog Tadpole", "type": "Processed" },
  { "name": "Glittering Steel Ingot", "type": "Processed" },
  { "name": "Gloom Bolt", "type": "Processed" },
  { "name": "Gloom Thread", "type": "Processed" },
  { "name": "Gloomy Pross Mulch", "type": "Processed" },
  { "name": "Gloomy Pross Powder", "type": "Processed" },
  { "name": "Gold Ingot", "type": "Processed" },
  { "name": "Granite Armor Mold", "type": "Processed" },
  { "name": "Granite Ashlar Block", "type": "Processed" },
  { "name": "Granite Brick", "type": "Processed" },
  { "name": "Granite Clay", "type": "Processed" },
  { "name": "Granite Fragments", "type": "Processed" },
  { "name": "Granite Mortar", "type": "Processed" },
  { "name": "Granite Sand", "type": "Processed" },
  { "name": "Granite Weapon Mold", "type": "Processed" },
  { "name": "Grave Bolt", "type": "Processed" },
  { "name": "Grave Lily Mulch", "type": "Processed" },
  { "name": "Grave Lily Powder", "type": "Processed" },
  { "name": "Grave Thread", "type": "Processed" },
  { "name": "Green Ink", "type": "Processed" },
  { "name": "Grem Bone", "type": "Processed" },
  { "name": "Grem Carcass", "type": "Processed" },
  { "name": "Grem Leather", "type": "Processed" },
  { "name": "Grem Meat", "type": "Processed" },
  { "name": "Grem Skin", "type": "Processed" },
  { "name": "Gryphon Bone", "type": "Processed" },
  { "name": "Gryphon Carcass", "type": "Processed" },
  { "name": "Gryphon Feather", "type": "Processed" },
  { "name": "Gryphon Hatchling", "type": "Processed" },
  { "name": "Gryphon Hide", "type": "Processed" },
  { "name": "Gryphon Leather", "type": "Processed" },
  { "name": "Gryphon Meat", "type": "Processed" },
  { "name": "Halcyonite Powder", "type": "Processed" },
  { "name": "Hay", "type": "Processed" },
  { "name": "Honey Comb", "type": "Processed" },
  { "name": "Hops", "type": "Processed" },
  { "name": "Horse Foal", "type": "Processed" },
  { "name": "Humulus Lupulus", "type": "Processed" },
  { "name": "Iron Armor Plating", "type": "Processed" },
  { "name": "Iron Chain Mail", "type": "Processed" },
  { "name": "Iron Fragments", "type": "Processed" },
  { "name": "Iron Ingot", "type": "Processed" },
  { "name": "Kindling", "type": "Processed" },
  { "name": "Kirin Carcass", "type": "Processed" },
  { "name": "Lamprey", "type": "Processed" },
  { "name": "Largemouth Bass", "type": "Processed" },
  { "name": "Leather Polish", "type": "Processed" },
  { "name": "Lettuce", "type": "Processed" },
  { "name": "Limestone Armor Mold", "type": "Processed" },
  { "name": "Limestone Ashlar Block", "type": "Processed" },
  { "name": "Limestone Basket Mold", "type": "Processed" },
  { "name": "Limestone Brick", "type": "Processed" },
  { "name": "Limestone Clay", "type": "Processed" },
  { "name": "Limestone Fragments", "type": "Processed" },
  { "name": "Limestone Mortar", "type": "Processed" },
  { "name": "Limestone Sand", "type": "Processed" },
  { "name": "Limestone Weapon Mold", "type": "Processed" },
  { "name": "Linen Bolt", "type": "Processed" },
  { "name": "Linen Tassel", "type": "Processed" },
  { "name": "Linen Thread", "type": "Processed" },
  { "name": "Liquid Honey", "type": "Processed" },
  { "name": "Lumadon Powder", "type": "Processed" },
  { "name": "Magic Powder", "type": "Processed" },
  { "name": "Malted Barley", "type": "Processed" },
  { "name": "Malted Corn", "type": "Processed" },
  { "name": "Malted Wheat", "type": "Processed" },
  { "name": "Midnight Mare Foal", "type": "Processed" },
  { "name": "Mirepoix", "type": "Processed" },
  { "name": "Molten Brass", "type": "Processed" },
  { "name": "Molten Bronze", "type": "Processed" },
  { "name": "Molten Copper", "type": "Processed" },
  { "name": "Molten Core", "type": "Processed" },
  { "name": "Molten Iron", "type": "Processed" },
  { "name": "Molten Rividium", "type": "Processed" },
  { "name": "Molten Steel", "type": "Processed" },
  { "name": "Molten Tin", "type": "Processed" },
  { "name": "Molten Zinc", "type": "Processed" },
  { "name": "Moon Bolt", "type": "Processed" },
  { "name": "Moon Thread", "type": "Processed" },
  { "name": "Moonbell Powder", "type": "Processed" },
  { "name": "Mystic Lens", "type": "Processed" },
  { "name": "Noodles", "type": "Processed" },
  { "name": "Notarized Siege Contract", "type": "Processed" },
  { "name": "Oak Beam", "type": "Processed" },
  { "name": "Oak Board", "type": "Processed" },
  { "name": "Oak Log", "type": "Processed" },
  { "name": "Oak Mulch", "type": "Processed" },
  { "name": "Oak Paper", "type": "Processed" },
  { "name": "Oak Plating", "type": "Processed" },
  { "name": "Oak Plank", "type": "Processed" },
  { "name": "Oak Saw Dust", "type": "Processed" },
  { "name": "Oak Timber", "type": "Processed" },
  { "name": "Oak Warp", "type": "Processed" },
  { "name": "Oak Woodchips", "type": "Processed" },
  { "name": "Plumed Haleberder Chick", "type": "Processed" },
  { "name": "Polished Emerald", "type": "Processed" },
  { "name": "Polished Halcyonite", "type": "Processed" },
  { "name": "Polished Lumadon", "type": "Processed" },
  { "name": "Polished Ruby", "type": "Processed" },
  { "name": "Polished Sapphire", "type": "Processed" },
  { "name": "Polishing Oil", "type": "Processed" },
  { "name": "Pork", "type": "Processed" },
  { "name": "Pridesnapper Cub", "type": "Processed" },
  { "name": "Protector's Pride Cub", "type": "Processed" },
  { "name": "Raptor Bone", "type": "Processed" },
  { "name": "Raptor Carcass", "type": "Processed" },
  { "name": "Raptor Hide", "type": "Processed" },
  { "name": "Raptor Leather", "type": "Processed" },
  { "name": "Raptor Meat", "type": "Processed" },
  { "name": "Raptor Nestling", "type": "Processed" },
  { "name": "Raptor Scale", "type": "Processed" },
  { "name": "Raven Bone", "type": "Processed" },
  { "name": "Raven Carcass", "type": "Processed" },
  { "name": "Raven Feather", "type": "Processed" },
  { "name": "Raven Leather", "type": "Processed" },
  { "name": "Raven Meat", "type": "Processed" },
  { "name": "Raven Skin", "type": "Processed" },
  { "name": "Red Ink", "type": "Processed" },
  { "name": "Riverdance Otter Carcass", "type": "Processed" },
  { "name": "Riverdancer Otter Meat", "type": "Processed" },
  { "name": "Riverdancer Otter Pup", "type": "Processed" },
  { "name": "Rividium Armor Plating", "type": "Processed" },
  { "name": "Rividium Chain Mail", "type": "Processed" },
  { "name": "Rividium Fragments", "type": "Processed" },
  { "name": "Rividium Ingot", "type": "Processed" },
  { "name": "Ruby Powder", "type": "Processed" },
  { "name": "Runic Steed Foal", "type": "Processed" },
  { "name": "Salmon", "type": "Processed" },
  { "name": "Sanctus Sauce", "type": "Processed" },
  { "name": "Sapphire Powder", "type": "Processed" },
  { "name": "Scatterclaw Pup", "type": "Processed" },
  { "name": "Sheep Carcass", "type": "Processed" },
  { "name": "Sheep Carcass", "type": "Processed" },
  { "name": "Sheep Feed", "type": "Processed" },
  { "name": "Sheep Meat", "type": "Processed" },
  { "name": "Shell Of The Ancients Hatchling", "type": "Processed" },
  { "name": "Shoddy Granite Ashlar Block", "type": "Processed" },
  { "name": "Siege Banner Pole", "type": "Processed" },
  { "name": "Silk Bolt", "type": "Processed" },
  { "name": "Silk Thread", "type": "Processed" },
  { "name": "Silver Ingot", "type": "Processed" },
  { "name": "Skinwalker Bone", "type": "Processed" },
  { "name": "Skinwalker Carcass", "type": "Processed" },
  { "name": "Skinwalker Hide", "type": "Processed" },
  { "name": "Skinwalker Leather", "type": "Processed" },
  { "name": "Skinwalker Meat", "type": "Processed" },
  { "name": "Skinwalker Pup", "type": "Processed" },
  { "name": "Slate Armor Mold", "type": "Processed" },
  { "name": "Slate Ashlar Block", "type": "Processed" },
  { "name": "Slate Basket Mold", "type": "Processed" },
  { "name": "Slate Brick", "type": "Processed" },
  { "name": "Slate Clay", "type": "Processed" },
  { "name": "Slate Fragments", "type": "Processed" },
  { "name": "Slate Mortar", "type": "Processed" },
  { "name": "Slate Sand", "type": "Processed" },
  { "name": "Slate Weapon Mold", "type": "Processed" },
  { "name": "Snowdrop Bolt", "type": "Processed" },
  { "name": "Snowdrop Mulch", "type": "Processed" },
  { "name": "Snowdrop Powder", "type": "Processed" },
  { "name": "Snowdrop Thread", "type": "Processed" },
  { "name": "Sodium Carbonate", "type": "Processed" },
  { "name": "Spider Carapace", "type": "Processed" },
  { "name": "Spider Carcass", "type": "Processed" },
  { "name": "Spider Silk Bolt", "type": "Processed" },
  { "name": "Spider Silk Lace", "type": "Processed" },
  { "name": "Spider Silk Thread", "type": "Processed" },
  { "name": "Spindlehemp Bolt", "type": "Processed" },
  { "name": "Spindlehemp Thread", "type": "Processed" },
  { "name": "Spindlevine Mulch", "type": "Processed" },
  { "name": "Spindlevine Powder", "type": "Processed" },
  { "name": "Stable Snowdrop Powder", "type": "Processed" },
  { "name": "Steel Armor Plating", "type": "Processed" },
  { "name": "Steel Chain Mail", "type": "Processed" },
  { "name": "Steel Ingot", "type": "Processed" },
  { "name": "Stellarium Ingot", "type": "Processed" },
  { "name": "Sugar", "type": "Processed" },
  { "name": "Tanned Bear Hide", "type": "Processed" },
  { "name": "Tanned Boar Hide", "type": "Processed" },
  { "name": "Tanned Giant Bullywog Hide", "type": "Processed" },
  { "name": "Tanned Grem Skin", "type": "Processed" },
  { "name": "Tanned Gryphon Hide", "type": "Processed" },
  { "name": "Tanned Otter Hide", "type": "Processed" },
  { "name": "Tanned Raptor Hide", "type": "Processed" },
  { "name": "Tanned Raven Skin", "type": "Processed" },
  { "name": "Tanned Skinwalker Hide", "type": "Processed" },
  { "name": "Tanned Wolf Hide", "type": "Processed" },
  { "name": "Tanned Wyrmling Hide", "type": "Processed" },
  { "name": "Tannin", "type": "Processed" },
  { "name": "Tanning Oil", "type": "Processed" },
  { "name": "Tidesnapper Hatchling", "type": "Processed" },
  { "name": "Timeless Terrapin Hatchling", "type": "Processed" },
  { "name": "Tin Armor Plating", "type": "Processed" },
  { "name": "Tin Chain Mail", "type": "Processed" },
  { "name": "Tin Fragments", "type": "Processed" },
  { "name": "Tin Ingot", "type": "Processed" },
  { "name": "Tomato", "type": "Processed" },
  { "name": "Tomato Sauce", "type": "Processed" },
  { "name": "Utility Gadget", "type": "Processed" },
  { "name": "Veshian Komodo Hatchling", "type": "Processed" },
  { "name": "Vinegar", "type": "Processed" },
  { "name": "Weathered Oak Timber", "type": "Processed" },
  { "name": "Weeping Willow Beam", "type": "Processed" },
  { "name": "Weeping Willow Board", "type": "Processed" },
  { "name": "Weeping Willow Log", "type": "Processed" },
  { "name": "Weeping Willow Mulch", "type": "Processed" },
  { "name": "Weeping Willow Paper", "type": "Processed" },
  { "name": "Weeping Willow Plating", "type": "Processed" },
  { "name": "Weeping Willow Plank", "type": "Processed" },
  { "name": "Weeping Willow Saw Dust", "type": "Processed" },
  { "name": "Weeping Willow Timber", "type": "Processed" },
  { "name": "Weeping Willow Warp", "type": "Processed" },
  { "name": "Weeping Willow Woodchips", "type": "Processed" },
  { "name": "Western Larch Beam", "type": "Processed" },
  { "name": "Western Larch Board", "type": "Processed" },
  { "name": "Western Larch Log", "type": "Processed" },
  { "name": "Western Larch Mulch", "type": "Processed" },
  { "name": "Western Larch Paper", "type": "Processed" },
  { "name": "Western Larch Plating", "type": "Processed" },
  { "name": "Western Larch Plank", "type": "Processed" },
  { "name": "Western Larch Saw Dust", "type": "Processed" },
  { "name": "Western Larch Timber", "type": "Processed" },
  { "name": "Western Larch Warp", "type": "Processed" },
  { "name": "Western Larch Woodchips", "type": "Processed" },
  { "name": "Wheat", "type": "Processed" },
  { "name": "White Ink", "type": "Processed" },
  { "name": "Wolf Bones", "type": "Processed" },
  { "name": "Wolf Carcass", "type": "Processed" },
  { "name": "Wolf Fur", "type": "Processed" },
  { "name": "Wolf Hide", "type": "Processed" },
  { "name": "Wolf Hide Strap", "type": "Processed" },
  { "name": "Wolf Leather", "type": "Processed" },
  { "name": "Wolf Meat", "type": "Processed" },
  { "name": "Wolf Pup", "type": "Processed" },d
  { "name": "Wood Oil", "type": "Processed" },
  { "name": "Wool", "type": "Processed" },
  { "name": "Wool Bolt", "type": "Processed" },
  { "name": "Wool Thread", "type": "Processed" },
  { "name": "Wyndstone Armor Mold", "type": "Processed" },
  { "name": "Wyndstone Basket Mold", "type": "Processed" },
  { "name": "Wyndstone Brick", "type": "Processed" },
  { "name": "Wyndstone Clay", "type": "Processed" },
  { "name": "Wyndstone Fragments", "type": "Processed" },
  { "name": "Wyndstone Mortar", "type": "Processed" },
  { "name": "Wyndstone Sand", "type": "Processed" },
  { "name": "Wyndstone Weapon Mold", "type": "Processed" },
  { "name": "Wyrmling Bone", "type": "Processed" },
  { "name": "Wyrmling Carcass", "type": "Processed" },
  { "name": "Wyrmling Hatchling", "type": "Processed" },
  { "name": "Wyrmling Hide", "type": "Processed" },
  { "name": "Wyrmling Leather", "type": "Processed" },
  { "name": "Wyrmling Meat", "type": "Processed" },
  { "name": "Wyrmling Scale", "type": "Processed" },
  { "name": "Yeast", "type": "Processed" },
  { "name": "Yellow Ink", "type": "Processed" },
  { "name": "Zinc Armor Plating", "type": "Processed" },
  { "name": "Zinc Chain Mail", "type": "Processed" },
  { "name": "Zinc Fragments", "type": "Processed" },
  { "name": "Zinc Ingot", "type": "Processed" }
  
  
]
